{
  "name": "destroyImage",
  "ns": "pkgcloud",
  "title": "Destroy Image",
  "description": "Destroy Image",
  "phrases": {
    "active": "Destroying image"
  },
  "ports": {
    "input": {
      "client": {
        "title": "Client",
        "type": "object",
        "required": true
      },
      "image": {
        "title": "Image",
        "type": "object",
        "required": true
      }
    },
    "output": {
      "err": {
        "title": "Error",
        "type": "object"
      },
      "success": {
        "title": "Success",
        "type": "object"
      }
    }
  }
}
